ur_resources/__init__.py
ur_resources/py.typed
UncountableURResources-0.0.7.dist-info/METADATA
UncountableURResources-0.0.7.dist-info/WHEEL
UncountableURResources-0.0.7.dist-info/top_level.txt
UncountableURResources-0.0.7.dist-info/RECORD
